CodingRider/__init__.py
CodingRider/__main__.py
CodingRider/crc.py
CodingRider/drone.py
CodingRider/protocol.py
CodingRider/receiver.py
CodingRider/storage.py
CodingRider/system.py
CodingRider/update.py
CodingRider/tools/__init__.py
CodingRider/tools/parser.py
CodingRider/tools/update.py
CodingRider-2.9.dist-info/LICENSE
CodingRider-2.9.dist-info/METADATA
CodingRider-2.9.dist-info/WHEEL
CodingRider-2.9.dist-info/top_level.txt
CodingRider-2.9.dist-info/RECORD
