Metadata-Version: 2.1
Name: CodingRider
Version: 2.9
Summary: Library for CodingRider
Home-page: https://imssam.me/shop/view.php?index_no=4031
Author: ALUX
Author-email: devdrone@aluxonline.com
License-File: LICENSE
Requires-Dist: pyserial >=3.4
Requires-Dist: numpy >=1.15.4
Requires-Dist: colorama >=0.4.0
